[
  {
    "price":3.696876599,
    "volume":269157048.8036498427,
    "marketcap":3662466671.4613242149,
    "zero_balance_addresses_all_time":8018.0,
    "unique_addresses_all_time":12698.0,
    "new_addresses":0.0,
    "active_addresses":0.0,
    "transaction_count":0.0,
    "transaction_count_all_time":0.0,
    "large_transaction_count":0.0,
    "average_transaction_value":0.0,
    "token_holder":4680.0,
    "time":1613779200000
  },
  {
    "price":3.5753572974,
    "volume":177759958.1180490255,
    "marketcap":3575782092.2239208221,
    "zero_balance_addresses_all_time":8018.0,
    "unique_addresses_all_time":12698.0,
    "new_addresses":0.0,
    "active_addresses":0.0,
    "transaction_count":0.0,
    "transaction_count_all_time":0.0,
    "large_transaction_count":0.0,
    "average_transaction_value":0.0,
    "token_holder":4680.0,
    "time":1613865600000
  },
  {
    "price":3.3546565009,
    "volume":296203482.2298684716,
    "marketcap":3356055517.6819238663,
    "zero_balance_addresses_all_time":8018.0,
    "unique_addresses_all_time":12698.0,
    "new_addresses":0.0,
    "active_addresses":0.0,
    "transaction_count":0.0,
    "transaction_count_all_time":0.0,
    "large_transaction_count":0.0,
    "average_transaction_value":0.0,
    "token_holder":4680.0,
    "time":1613952000000
  },
  {
    "price":3.0551083723,
    "volume":333562934.6511380076,
    "marketcap":3042434158.1721978188,
    "zero_balance_addresses_all_time":8018.0,
    "unique_addresses_all_time":12698.0,
    "new_addresses":0.0,
    "active_addresses":0.0,
    "transaction_count":0.0,
    "transaction_count_all_time":0.0,
    "large_transaction_count":0.0,
    "average_transaction_value":0.0,
    "token_holder":4680.0,
    "time":1614038400000
  },
  {
    "price":3.3295678706,
    "volume":265180409.4530617893,
    "marketcap":3332914754.8088870049,
    "zero_balance_addresses_all_time":8018.0,
    "unique_addresses_all_time":12698.0,
    "new_addresses":0.0,
    "active_addresses":0.0,
    "transaction_count":0.0,
    "transaction_count_all_time":0.0,
    "large_transaction_count":0.0,
    "average_transaction_value":0.0,
    "token_holder":4680.0,
    "time":1614124800000
  },
  {
    "price":2.9758404374,
    "volume":196849640.9219939709,
    "marketcap":2993900169.8921480179,
    "zero_balance_addresses_all_time":8018.0,
    "unique_addresses_all_time":12698.0,
    "new_addresses":0.0,
    "active_addresses":0.0,
    "transaction_count":0.0,
    "transaction_count_all_time":0.0,
    "large_transaction_count":0.0,
    "average_transaction_value":0.0,
    "token_holder":4680.0,
    "time":1614211200000
  },
  {
    "price":3.0625938562,
    "volume":202691004.2796633244,
    "marketcap":3073420041.5062990189,
    "zero_balance_addresses_all_time":8018.0,
    "unique_addresses_all_time":12698.0,
    "new_addresses":0.0,
    "active_addresses":0.0,
    "transaction_count":0.0,
    "transaction_count_all_time":0.0,
    "large_transaction_count":0.0,
    "average_transaction_value":0.0,
    "token_holder":4680.0,
    "time":1614297600000
  },
  {
    "price":3.1911635532,
    "volume":176811978.3280454874,
    "marketcap":3147601125.3400568962,
    "zero_balance_addresses_all_time":8018.0,
    "unique_addresses_all_time":12698.0,
    "new_addresses":0.0,
    "active_addresses":0.0,
    "transaction_count":0.0,
    "transaction_count_all_time":0.0,
    "large_transaction_count":0.0,
    "average_transaction_value":0.0,
    "token_holder":4680.0,
    "time":1614384000000
  },
  {
    "price":3.1279335142,
    "volume":183118511.9718284309,
    "marketcap":3147795602.4165058136,
    "zero_balance_addresses_all_time":8018.0,
    "unique_addresses_all_time":12698.0,
    "new_addresses":0.0,
    "active_addresses":0.0,
    "transaction_count":0.0,
    "transaction_count_all_time":0.0,
    "large_transaction_count":0.0,
    "average_transaction_value":0.0,
    "token_holder":4680.0,
    "time":1614470400000
  },
  {
    "price":3.2827014386,
    "volume":162909999.5103544295,
    "marketcap":3285741644.3785338402,
    "zero_balance_addresses_all_time":8018.0,
    "unique_addresses_all_time":12698.0,
    "new_addresses":0.0,
    "active_addresses":0.0,
    "transaction_count":0.0,
    "transaction_count_all_time":0.0,
    "large_transaction_count":0.0,
    "average_transaction_value":0.0,
    "token_holder":4680.0,
    "time":1614556800000
  },
  {
    "price":3.7383835987,
    "volume":470777349.7176670432,
    "marketcap":3740967899.8587532043,
    "zero_balance_addresses_all_time":8018.0,
    "unique_addresses_all_time":12698.0,
    "new_addresses":0.0,
    "active_addresses":0.0,
    "transaction_count":0.0,
    "transaction_count_all_time":0.0,
    "large_transaction_count":0.0,
    "average_transaction_value":0.0,
    "token_holder":4680.0,
    "time":1614643200000
  },
  {
    "price":3.9899692548,
    "volume":333564955.2541491985,
    "marketcap":3992477601.3828787804,
    "zero_balance_addresses_all_time":8018.0,
    "unique_addresses_all_time":12698.0,
    "new_addresses":0.0,
    "active_addresses":0.0,
    "transaction_count":0.0,
    "transaction_count_all_time":0.0,
    "large_transaction_count":0.0,
    "average_transaction_value":0.0,
    "token_holder":4680.0,
    "time":1614729600000
  },
  {
    "price":4.4880088578,
    "volume":445729783.4775104523,
    "marketcap":4547648621.7901248932,
    "zero_balance_addresses_all_time":8018.0,
    "unique_addresses_all_time":12698.0,
    "new_addresses":0.0,
    "active_addresses":0.0,
    "transaction_count":0.0,
    "transaction_count_all_time":0.0,
    "large_transaction_count":0.0,
    "average_transaction_value":0.0,
    "token_holder":4680.0,
    "time":1614816000000
  },
  {
    "price":4.1521627229,
    "volume":479474815.0640685558,
    "marketcap":4101714904.8038430214,
    "zero_balance_addresses_all_time":8018.0,
    "unique_addresses_all_time":12698.0,
    "new_addresses":0.0,
    "active_addresses":0.0,
    "transaction_count":0.0,
    "transaction_count_all_time":0.0,
    "large_transaction_count":0.0,
    "average_transaction_value":0.0,
    "token_holder":4680.0,
    "time":1614902400000
  },
  {
    "price":4.1648765017,
    "volume":232275546.3634543717,
    "marketcap":4157860704.7837939262,
    "zero_balance_addresses_all_time":8018.0,
    "unique_addresses_all_time":12698.0,
    "new_addresses":0.0,
    "active_addresses":0.0,
    "transaction_count":0.0,
    "transaction_count_all_time":0.0,
    "large_transaction_count":0.0,
    "average_transaction_value":0.0,
    "token_holder":4680.0,
    "time":1614988800000
  },
  {
    "price":4.3526043469,
    "volume":207431832.4054633081,
    "marketcap":4350460434.5458536148,
    "zero_balance_addresses_all_time":8018.0,
    "unique_addresses_all_time":12698.0,
    "new_addresses":0.0,
    "active_addresses":0.0,
    "transaction_count":0.0,
    "transaction_count_all_time":0.0,
    "large_transaction_count":0.0,
    "average_transaction_value":0.0,
    "token_holder":4680.0,
    "time":1615075200000
  },
  {
    "price":4.9004447197,
    "volume":370402503.162948072,
    "marketcap":4904429334.6581907272,
    "zero_balance_addresses_all_time":8018.0,
    "unique_addresses_all_time":12698.0,
    "new_addresses":0.0,
    "active_addresses":0.0,
    "transaction_count":0.0,
    "transaction_count_all_time":0.0,
    "large_transaction_count":0.0,
    "average_transaction_value":0.0,
    "token_holder":4680.0,
    "time":1615161600000
  },
  {
    "price":5.3865159621,
    "volume":365079372.1637125015,
    "marketcap":5370006053.6204843521,
    "zero_balance_addresses_all_time":8018.0,
    "unique_addresses_all_time":12698.0,
    "new_addresses":0.0,
    "active_addresses":0.0,
    "transaction_count":0.0,
    "transaction_count_all_time":0.0,
    "large_transaction_count":0.0,
    "average_transaction_value":0.0,
    "token_holder":4680.0,
    "time":1615248000000
  },
  {
    "price":6.5628464221,
    "volume":535887145.7579359412,
    "marketcap":6621563126.723484993,
    "zero_balance_addresses_all_time":8018.0,
    "unique_addresses_all_time":12698.0,
    "new_addresses":0.0,
    "active_addresses":0.0,
    "transaction_count":0.0,
    "transaction_count_all_time":0.0,
    "large_transaction_count":0.0,
    "average_transaction_value":0.0,
    "token_holder":4680.0,
    "time":1615334400000
  },
  {
    "price":6.9761897392,
    "volume":1396089741.6023566723,
    "marketcap":6944499170.2186517715,
    "zero_balance_addresses_all_time":8018.0,
    "unique_addresses_all_time":12698.0,
    "new_addresses":0.0,
    "active_addresses":0.0,
    "transaction_count":0.0,
    "transaction_count_all_time":0.0,
    "large_transaction_count":0.0,
    "average_transaction_value":0.0,
    "token_holder":4680.0,
    "time":1615420800000
  },
  {
    "price":6.9844750236,
    "volume":875604885.0052822828,
    "marketcap":6994315671.3403959274,
    "zero_balance_addresses_all_time":8018.0,
    "unique_addresses_all_time":12698.0,
    "new_addresses":0.0,
    "active_addresses":0.0,
    "transaction_count":0.0,
    "transaction_count_all_time":0.0,
    "large_transaction_count":0.0,
    "average_transaction_value":0.0,
    "token_holder":4680.0,
    "time":1615507200000
  },
  {
    "price":6.8452287568,
    "volume":436912163.6860697865,
    "marketcap":6848077039.9057283401,
    "zero_balance_addresses_all_time":8018.0,
    "unique_addresses_all_time":12698.0,
    "new_addresses":0.0,
    "active_addresses":0.0,
    "transaction_count":0.0,
    "transaction_count_all_time":0.0,
    "large_transaction_count":0.0,
    "average_transaction_value":0.0,
    "token_holder":4680.0,
    "time":1615593600000
  },
  {
    "price":7.4592378801,
    "volume":710558672.1432324648,
    "marketcap":7513821401.0051012039,
    "zero_balance_addresses_all_time":8018.0,
    "unique_addresses_all_time":12698.0,
    "new_addresses":0.0,
    "active_addresses":0.0,
    "transaction_count":0.0,
    "transaction_count_all_time":0.0,
    "large_transaction_count":0.0,
    "average_transaction_value":0.0,
    "token_holder":4680.0,
    "time":1615680000000
  },
  {
    "price":6.7616190735,
    "volume":454412911.0761796236,
    "marketcap":6800777426.5089979172,
    "zero_balance_addresses_all_time":8018.0,
    "unique_addresses_all_time":12698.0,
    "new_addresses":0.0,
    "active_addresses":0.0,
    "transaction_count":0.0,
    "transaction_count_all_time":0.0,
    "large_transaction_count":0.0,
    "average_transaction_value":0.0,
    "token_holder":4680.0,
    "time":1615766400000
  },
  {
    "price":7.0468767603,
    "volume":453475287.4644667506,
    "marketcap":7017735947.6381874084,
    "zero_balance_addresses_all_time":8018.0,
    "unique_addresses_all_time":12698.0,
    "new_addresses":0.0,
    "active_addresses":0.0,
    "transaction_count":0.0,
    "transaction_count_all_time":0.0,
    "large_transaction_count":0.0,
    "average_transaction_value":0.0,
    "token_holder":4680.0,
    "time":1615852800000
  },
  {
    "price":7.8508860942,
    "volume":340141458.5987153053,
    "marketcap":7780103945.9209661484,
    "zero_balance_addresses_all_time":8018.0,
    "unique_addresses_all_time":12698.0,
    "new_addresses":0.0,
    "active_addresses":0.0,
    "transaction_count":0.0,
    "transaction_count_all_time":0.0,
    "large_transaction_count":0.0,
    "average_transaction_value":0.0,
    "token_holder":4680.0,
    "time":1615939200000
  },
  {
    "price":8.4416416128,
    "volume":577866810.6507055759,
    "marketcap":8411995291.7236814499,
    "zero_balance_addresses_all_time":8018.0,
    "unique_addresses_all_time":12698.0,
    "new_addresses":0.0,
    "active_addresses":0.0,
    "transaction_count":0.0,
    "transaction_count_all_time":0.0,
    "large_transaction_count":0.0,
    "average_transaction_value":0.0,
    "token_holder":4680.0,
    "time":1616025600000
  },
  {
    "price":8.1986507099,
    "volume":513439307.0767777562,
    "marketcap":8212466381.811337471,
    "zero_balance_addresses_all_time":8018.0,
    "unique_addresses_all_time":12698.0,
    "new_addresses":0.0,
    "active_addresses":0.0,
    "transaction_count":0.0,
    "transaction_count_all_time":0.0,
    "large_transaction_count":0.0,
    "average_transaction_value":0.0,
    "token_holder":4680.0,
    "time":1616112000000
  },
  {
    "price":8.3693114654,
    "volume":319546856.7443580031,
    "marketcap":8405023570.3864078522,
    "zero_balance_addresses_all_time":8018.0,
    "unique_addresses_all_time":12698.0,
    "new_addresses":0.0,
    "active_addresses":0.0,
    "transaction_count":0.0,
    "transaction_count_all_time":0.0,
    "large_transaction_count":0.0,
    "average_transaction_value":0.0,
    "token_holder":4680.0,
    "time":1616198400000
  },
  {
    "price":9.5656002626,
    "volume":578632570.4468294382,
    "marketcap":9542831906.250421524,
    "zero_balance_addresses_all_time":8018.0,
    "unique_addresses_all_time":12698.0,
    "new_addresses":0.0,
    "active_addresses":0.0,
    "transaction_count":0.0,
    "transaction_count_all_time":0.0,
    "large_transaction_count":0.0,
    "average_transaction_value":0.0,
    "token_holder":4680.0,
    "time":1616284800000
  },
  {
    "price":10.1417813114,
    "volume":1009761627.4491262436,
    "marketcap":10273634913.2691192627,
    "zero_balance_addresses_all_time":8018.0,
    "unique_addresses_all_time":12698.0,
    "new_addresses":0.0,
    "active_addresses":0.0,
    "transaction_count":0.0,
    "transaction_count_all_time":0.0,
    "large_transaction_count":0.0,
    "average_transaction_value":0.0,
    "token_holder":4680.0,
    "time":1616371200000
  },
  {
    "price":13.0390074231,
    "volume":2577470830.2724738121,
    "marketcap":13178116548.2879505157,
    "zero_balance_addresses_all_time":8018.0,
    "unique_addresses_all_time":12698.0,
    "new_addresses":0.0,
    "active_addresses":0.0,
    "transaction_count":0.0,
    "transaction_count_all_time":0.0,
    "large_transaction_count":0.0,
    "average_transaction_value":0.0,
    "token_holder":4680.0,
    "time":1616457600000
  },
  {
    "price":11.3301515144,
    "volume":2191487662.8434147835,
    "marketcap":11365538756.9322891235,
    "zero_balance_addresses_all_time":8018.0,
    "unique_addresses_all_time":12698.0,
    "new_addresses":0.0,
    "active_addresses":0.0,
    "transaction_count":0.0,
    "transaction_count_all_time":0.0,
    "large_transaction_count":0.0,
    "average_transaction_value":0.0,
    "token_holder":4680.0,
    "time":1616544000000
  },
  {
    "price":13.0826800746,
    "volume":1940442506.522223711,
    "marketcap":13096379591.827999115,
    "zero_balance_addresses_all_time":8018.0,
    "unique_addresses_all_time":12698.0,
    "new_addresses":0.0,
    "active_addresses":0.0,
    "transaction_count":0.0,
    "transaction_count_all_time":0.0,
    "large_transaction_count":0.0,
    "average_transaction_value":0.0,
    "token_holder":4680.0,
    "time":1616630400000
  },
  {
    "price":12.4692053202,
    "volume":931406404.2298326492,
    "marketcap":12416691563.6914291382,
    "zero_balance_addresses_all_time":8018.0,
    "unique_addresses_all_time":12698.0,
    "new_addresses":0.0,
    "active_addresses":0.0,
    "transaction_count":0.0,
    "transaction_count_all_time":0.0,
    "large_transaction_count":0.0,
    "average_transaction_value":0.0,
    "token_holder":4680.0,
    "time":1616716800000
  },
  {
    "price":11.8421574528,
    "volume":620462496.5742133856,
    "marketcap":11879182277.2786598206,
    "zero_balance_addresses_all_time":8018.0,
    "unique_addresses_all_time":12698.0,
    "new_addresses":0.0,
    "active_addresses":0.0,
    "transaction_count":0.0,
    "transaction_count_all_time":0.0,
    "large_transaction_count":0.0,
    "average_transaction_value":0.0,
    "token_holder":4680.0,
    "time":1616803200000
  },
  {
    "price":12.8107229714,
    "volume":780762162.6053255796,
    "marketcap":12803449385.3190193176,
    "zero_balance_addresses_all_time":8018.0,
    "unique_addresses_all_time":12698.0,
    "new_addresses":0.0,
    "active_addresses":0.0,
    "transaction_count":0.0,
    "transaction_count_all_time":0.0,
    "large_transaction_count":0.0,
    "average_transaction_value":0.0,
    "token_holder":4680.0,
    "time":1616889600000
  },
  {
    "price":13.1276318957,
    "volume":832785749.5450642109,
    "marketcap":13120834411.673160553,
    "zero_balance_addresses_all_time":8018.0,
    "unique_addresses_all_time":12698.0,
    "new_addresses":0.0,
    "active_addresses":0.0,
    "transaction_count":0.0,
    "transaction_count_all_time":0.0,
    "large_transaction_count":0.0,
    "average_transaction_value":0.0,
    "token_holder":4680.0,
    "time":1616976000000
  },
  {
    "price":12.9468205752,
    "volume":490651186.9073053002,
    "marketcap":12949367808.5860404968,
    "zero_balance_addresses_all_time":8018.0,
    "unique_addresses_all_time":12698.0,
    "new_addresses":0.0,
    "active_addresses":0.0,
    "transaction_count":0.0,
    "transaction_count_all_time":0.0,
    "large_transaction_count":0.0,
    "average_transaction_value":0.0,
    "token_holder":4680.0,
    "time":1617062400000
  },
  {
    "price":12.2297267525,
    "volume":592172179.5257302523,
    "marketcap":12242179343.5321598053,
    "zero_balance_addresses_all_time":8018.0,
    "unique_addresses_all_time":12698.0,
    "new_addresses":0.0,
    "active_addresses":0.0,
    "transaction_count":0.0,
    "transaction_count_all_time":0.0,
    "large_transaction_count":0.0,
    "average_transaction_value":0.0,
    "token_holder":4680.0,
    "time":1617148800000
  },
  {
    "price":11.519977235,
    "volume":613639060.26689291,
    "marketcap":11514319689.053150177,
    "zero_balance_addresses_all_time":8018.0,
    "unique_addresses_all_time":12698.0,
    "new_addresses":0.0,
    "active_addresses":0.0,
    "transaction_count":0.0,
    "transaction_count_all_time":0.0,
    "large_transaction_count":0.0,
    "average_transaction_value":0.0,
    "token_holder":4680.0,
    "time":1617235200000
  },
  {
    "price":11.655353753,
    "volume":474926604.9678687453,
    "marketcap":11671063105.3046092987,
    "zero_balance_addresses_all_time":8018.0,
    "unique_addresses_all_time":12698.0,
    "new_addresses":0.0,
    "active_addresses":0.0,
    "transaction_count":0.0,
    "transaction_count_all_time":0.0,
    "large_transaction_count":0.0,
    "average_transaction_value":0.0,
    "token_holder":4680.0,
    "time":1617321600000
  },
  {
    "price":11.4332363862,
    "volume":491454460.6455235481,
    "marketcap":11470290250.787820816,
    "zero_balance_addresses_all_time":8018.0,
    "unique_addresses_all_time":12698.0,
    "new_addresses":0.0,
    "active_addresses":0.0,
    "transaction_count":0.0,
    "transaction_count_all_time":0.0,
    "large_transaction_count":0.0,
    "average_transaction_value":0.0,
    "token_holder":4680.0,
    "time":1617408000000
  },
  {
    "price":11.8208453343,
    "volume":281532087.4955696464,
    "marketcap":11817911062.2972507477,
    "zero_balance_addresses_all_time":8018.0,
    "unique_addresses_all_time":12698.0,
    "new_addresses":0.0,
    "active_addresses":0.0,
    "transaction_count":0.0,
    "transaction_count_all_time":0.0,
    "large_transaction_count":0.0,
    "average_transaction_value":0.0,
    "token_holder":4680.0,
    "time":1617494400000
  },
  {
    "price":11.5781273906,
    "volume":347451008.9800617695,
    "marketcap":11575527681.6890106201,
    "zero_balance_addresses_all_time":8018.0,
    "unique_addresses_all_time":12698.0,
    "new_addresses":0.0,
    "active_addresses":0.0,
    "transaction_count":0.0,
    "transaction_count_all_time":0.0,
    "large_transaction_count":0.0,
    "average_transaction_value":0.0,
    "token_holder":4680.0,
    "time":1617580800000
  },
  {
    "price":11.7167381817,
    "volume":377055087.9591860175,
    "marketcap":11701539766.7084007263,
    "zero_balance_addresses_all_time":8018.0,
    "unique_addresses_all_time":12698.0,
    "new_addresses":0.0,
    "active_addresses":0.0,
    "transaction_count":0.0,
    "transaction_count_all_time":0.0,
    "large_transaction_count":0.0,
    "average_transaction_value":0.0,
    "token_holder":4680.0,
    "time":1617667200000
  },
  {
    "price":12.3065417953,
    "volume":1437810418.5219917297,
    "marketcap":12378894545.9562892914,
    "zero_balance_addresses_all_time":8018.0,
    "unique_addresses_all_time":12698.0,
    "new_addresses":0.0,
    "active_addresses":0.0,
    "transaction_count":0.0,
    "transaction_count_all_time":0.0,
    "large_transaction_count":0.0,
    "average_transaction_value":0.0,
    "token_holder":4680.0,
    "time":1617753600000
  },
  {
    "price":12.9057107834,
    "volume":601823634.6601518393,
    "marketcap":12924673739.9501399994,
    "zero_balance_addresses_all_time":8018.0,
    "unique_addresses_all_time":12698.0,
    "new_addresses":0.0,
    "active_addresses":0.0,
    "transaction_count":0.0,
    "transaction_count_all_time":0.0,
    "large_transaction_count":0.0,
    "average_transaction_value":0.0,
    "token_holder":4680.0,
    "time":1617840000000
  },
  {
    "price":12.6016852428,
    "volume":373489108.5528244972,
    "marketcap":12618069394.8064193726,
    "zero_balance_addresses_all_time":8018.0,
    "unique_addresses_all_time":12698.0,
    "new_addresses":0.0,
    "active_addresses":0.0,
    "transaction_count":0.0,
    "transaction_count_all_time":0.0,
    "large_transaction_count":0.0,
    "average_transaction_value":0.0,
    "token_holder":4680.0,
    "time":1617926400000
  },
  {
    "price":12.3959252242,
    "volume":347412210.658095181,
    "marketcap":12387525924.6082992554,
    "zero_balance_addresses_all_time":8018.0,
    "unique_addresses_all_time":12698.0,
    "new_addresses":0.0,
    "active_addresses":0.0,
    "transaction_count":0.0,
    "transaction_count_all_time":0.0,
    "large_transaction_count":0.0,
    "average_transaction_value":0.0,
    "token_holder":4680.0,
    "time":1618012800000
  },
  {
    "price":12.2181255422,
    "volume":275215215.6070732474,
    "marketcap":12197305948.2438392639,
    "zero_balance_addresses_all_time":8018.0,
    "unique_addresses_all_time":12698.0,
    "new_addresses":0.0,
    "active_addresses":0.0,
    "transaction_count":0.0,
    "transaction_count_all_time":0.0,
    "large_transaction_count":0.0,
    "average_transaction_value":0.0,
    "token_holder":4680.0,
    "time":1618099200000
  },
  {
    "price":12.1149713094,
    "volume":262331959.9598812461,
    "marketcap":12101031166.9612007141,
    "zero_balance_addresses_all_time":8018.0,
    "unique_addresses_all_time":12698.0,
    "new_addresses":0.0,
    "active_addresses":0.0,
    "transaction_count":0.0,
    "transaction_count_all_time":0.0,
    "large_transaction_count":0.0,
    "average_transaction_value":0.0,
    "token_holder":4680.0,
    "time":1618185600000
  },
  {
    "price":12.4844269574,
    "volume":427392752.9925885797,
    "marketcap":12491051348.8260097504,
    "zero_balance_addresses_all_time":8018.0,
    "unique_addresses_all_time":12698.0,
    "new_addresses":0.0,
    "active_addresses":0.0,
    "transaction_count":0.0,
    "transaction_count_all_time":0.0,
    "large_transaction_count":0.0,
    "average_transaction_value":0.0,
    "token_holder":4680.0,
    "time":1618272000000
  },
  {
    "price":12.1279805662,
    "volume":542185089.1537641287,
    "marketcap":12115583163.5757694244,
    "zero_balance_addresses_all_time":8018.0,
    "unique_addresses_all_time":12698.0,
    "new_addresses":0.0,
    "active_addresses":0.0,
    "transaction_count":0.0,
    "transaction_count_all_time":0.0,
    "large_transaction_count":0.0,
    "average_transaction_value":0.0,
    "token_holder":4680.0,
    "time":1618358400000
  },
  {
    "price":12.5620485963,
    "volume":318956543.3878545165,
    "marketcap":12536959053.9058208466,
    "zero_balance_addresses_all_time":8018.0,
    "unique_addresses_all_time":12698.0,
    "new_addresses":0.0,
    "active_addresses":0.0,
    "transaction_count":0.0,
    "transaction_count_all_time":0.0,
    "large_transaction_count":0.0,
    "average_transaction_value":0.0,
    "token_holder":4680.0,
    "time":1618444800000
  },
  {
    "price":14.100056416,
    "volume":1205161056.2956159115,
    "marketcap":14012980204.6491794586,
    "zero_balance_addresses_all_time":8018.0,
    "unique_addresses_all_time":12698.0,
    "new_addresses":0.0,
    "active_addresses":0.0,
    "transaction_count":0.0,
    "transaction_count_all_time":0.0,
    "large_transaction_count":0.0,
    "average_transaction_value":0.0,
    "token_holder":4680.0,
    "time":1618531200000
  },
  {
    "price":13.428248449,
    "volume":783208186.6330070496,
    "marketcap":13471456851.4432792664,
    "zero_balance_addresses_all_time":8018.0,
    "unique_addresses_all_time":12698.0,
    "new_addresses":0.0,
    "active_addresses":0.0,
    "transaction_count":0.0,
    "transaction_count_all_time":0.0,
    "large_transaction_count":0.0,
    "average_transaction_value":0.0,
    "token_holder":4680.0,
    "time":1618617600000
  },
  {
    "price":11.8686953539,
    "volume":1231283685.315456152,
    "marketcap":11868695353.9234008789,
    "zero_balance_addresses_all_time":8018.0,
    "unique_addresses_all_time":12698.0,
    "new_addresses":0.0,
    "active_addresses":0.0,
    "transaction_count":0.0,
    "transaction_count_all_time":0.0,
    "large_transaction_count":0.0,
    "average_transaction_value":0.0,
    "token_holder":4680.0,
    "time":1618704000000
  },
  {
    "price":10.8840239821,
    "volume":642929181.1457946301,
    "marketcap":10882060848.662689209,
    "zero_balance_addresses_all_time":8018.0,
    "unique_addresses_all_time":12698.0,
    "new_addresses":0.0,
    "active_addresses":0.0,
    "transaction_count":0.0,
    "transaction_count_all_time":0.0,
    "large_transaction_count":0.0,
    "average_transaction_value":0.0,
    "token_holder":4680.0,
    "time":1618790400000
  },
  {
    "price":11.6963486272,
    "volume":786537222.9090842009,
    "marketcap":11722359762.0151004791,
    "zero_balance_addresses_all_time":8018.0,
    "unique_addresses_all_time":12698.0,
    "new_addresses":0.0,
    "active_addresses":0.0,
    "transaction_count":0.0,
    "transaction_count_all_time":0.0,
    "large_transaction_count":0.0,
    "average_transaction_value":0.0,
    "token_holder":4680.0,
    "time":1618876800000
  },
  {
    "price":11.1007592663,
    "volume":509869301.7429650426,
    "marketcap":11162213382.3810005188,
    "zero_balance_addresses_all_time":8018.0,
    "unique_addresses_all_time":12698.0,
    "new_addresses":0.0,
    "active_addresses":0.0,
    "transaction_count":0.0,
    "transaction_count_all_time":0.0,
    "large_transaction_count":0.0,
    "average_transaction_value":0.0,
    "token_holder":4680.0,
    "time":1618963200000
  },
  {
    "price":10.0297456972,
    "volume":607155737.4246368408,
    "marketcap":10066383488.3032493591,
    "zero_balance_addresses_all_time":8018.0,
    "unique_addresses_all_time":12698.0,
    "new_addresses":0.0,
    "active_addresses":0.0,
    "transaction_count":0.0,
    "transaction_count_all_time":0.0,
    "large_transaction_count":0.0,
    "average_transaction_value":0.0,
    "token_holder":4680.0,
    "time":1619049600000
  },
  {
    "price":9.9708448027,
    "volume":1267545106.4492974281,
    "marketcap":9938002664.7070064545,
    "zero_balance_addresses_all_time":8018.0,
    "unique_addresses_all_time":12698.0,
    "new_addresses":0.0,
    "active_addresses":0.0,
    "transaction_count":0.0,
    "transaction_count_all_time":0.0,
    "large_transaction_count":0.0,
    "average_transaction_value":0.0,
    "token_holder":4680.0,
    "time":1619136000000
  },
  {
    "price":8.6472793545,
    "volume":513873892.5597428679,
    "marketcap":8701809002.4168949127,
    "zero_balance_addresses_all_time":8018.0,
    "unique_addresses_all_time":12698.0,
    "new_addresses":0.0,
    "active_addresses":0.0,
    "transaction_count":0.0,
    "transaction_count_all_time":0.0,
    "large_transaction_count":0.0,
    "average_transaction_value":0.0,
    "token_holder":4680.0,
    "time":1619222400000
  },
  {
    "price":9.0201321364,
    "volume":526845999.4199755192,
    "marketcap":8994186978.3775672913,
    "zero_balance_addresses_all_time":8018.0,
    "unique_addresses_all_time":12698.0,
    "new_addresses":0.0,
    "active_addresses":0.0,
    "transaction_count":0.0,
    "transaction_count_all_time":0.0,
    "large_transaction_count":0.0,
    "average_transaction_value":0.0,
    "token_holder":4680.0,
    "time":1619308800000
  },
  {
    "price":10.748472857,
    "volume":757971077.4531729221,
    "marketcap":10618191905.0343208313,
    "zero_balance_addresses_all_time":8018.0,
    "unique_addresses_all_time":12698.0,
    "new_addresses":0.0,
    "active_addresses":0.0,
    "transaction_count":0.0,
    "transaction_count_all_time":0.0,
    "large_transaction_count":0.0,
    "average_transaction_value":0.0,
    "token_holder":4680.0,
    "time":1619395200000
  },
  {
    "price":11.2207275002,
    "volume":442555419.9129633904,
    "marketcap":11200346915.8648605347,
    "zero_balance_addresses_all_time":8018.0,
    "unique_addresses_all_time":12698.0,
    "new_addresses":0.0,
    "active_addresses":0.0,
    "transaction_count":0.0,
    "transaction_count_all_time":0.0,
    "large_transaction_count":0.0,
    "average_transaction_value":0.0,
    "token_holder":4680.0,
    "time":1619481600000
  },
  {
    "price":11.0570191771,
    "volume":395206023.869248569,
    "marketcap":11033027265.3290901184,
    "zero_balance_addresses_all_time":8018.0,
    "unique_addresses_all_time":12698.0,
    "new_addresses":0.0,
    "active_addresses":0.0,
    "transaction_count":0.0,
    "transaction_count_all_time":0.0,
    "large_transaction_count":0.0,
    "average_transaction_value":0.0,
    "token_holder":4680.0,
    "time":1619568000000
  },
  {
    "price":10.9231082746,
    "volume":351065734.9770103097,
    "marketcap":10942892353.3396701813,
    "zero_balance_addresses_all_time":8018.0,
    "unique_addresses_all_time":12698.0,
    "new_addresses":0.0,
    "active_addresses":0.0,
    "transaction_count":0.0,
    "transaction_count_all_time":0.0,
    "large_transaction_count":0.0,
    "average_transaction_value":0.0,
    "token_holder":4680.0,
    "time":1619654400000
  },
  {
    "price":11.2110508593,
    "volume":291389002.2419680953,
    "marketcap":11185911208.1599006653,
    "zero_balance_addresses_all_time":8018.0,
    "unique_addresses_all_time":12698.0,
    "new_addresses":0.0,
    "active_addresses":0.0,
    "transaction_count":0.0,
    "transaction_count_all_time":0.0,
    "large_transaction_count":0.0,
    "average_transaction_value":0.0,
    "token_holder":4680.0,
    "time":1619740800000
  },
  {
    "price":11.4677762703,
    "volume":372182772.3712030053,
    "marketcap":11459697279.4949798584,
    "zero_balance_addresses_all_time":8018.0,
    "unique_addresses_all_time":12698.0,
    "new_addresses":0.0,
    "active_addresses":0.0,
    "transaction_count":0.0,
    "transaction_count_all_time":0.0,
    "large_transaction_count":0.0,
    "average_transaction_value":0.0,
    "token_holder":4680.0,
    "time":1619827200000
  },
  {
    "price":10.9768973903,
    "volume":298946100.9646458626,
    "marketcap":10952421277.5680503845,
    "zero_balance_addresses_all_time":8018.0,
    "unique_addresses_all_time":12698.0,
    "new_addresses":0.0,
    "active_addresses":0.0,
    "transaction_count":0.0,
    "transaction_count_all_time":0.0,
    "large_transaction_count":0.0,
    "average_transaction_value":0.0,
    "token_holder":4680.0,
    "time":1619913600000
  },
  {
    "price":11.578305639,
    "volume":515751884.7735034823,
    "marketcap":11614316815.2158603668,
    "zero_balance_addresses_all_time":8018.0,
    "unique_addresses_all_time":12698.0,
    "new_addresses":0.0,
    "active_addresses":0.0,
    "transaction_count":0.0,
    "transaction_count_all_time":0.0,
    "large_transaction_count":0.0,
    "average_transaction_value":0.0,
    "token_holder":4680.0,
    "time":1620000000000
  },
  {
    "price":10.2278026538,
    "volume":527552612.2493026257,
    "marketcap":10304680559.1187400818,
    "zero_balance_addresses_all_time":8018.0,
    "unique_addresses_all_time":12698.0,
    "new_addresses":0.0,
    "active_addresses":0.0,
    "transaction_count":0.0,
    "transaction_count_all_time":0.0,
    "large_transaction_count":0.0,
    "average_transaction_value":0.0,
    "token_holder":4680.0,
    "time":1620086400000
  },
  {
    "price":10.9659977991,
    "volume":403769888.3832198381,
    "marketcap":10960079216.7896308899,
    "zero_balance_addresses_all_time":8018.0,
    "unique_addresses_all_time":12698.0,
    "new_addresses":0.0,
    "active_addresses":0.0,
    "transaction_count":0.0,
    "transaction_count_all_time":0.0,
    "large_transaction_count":0.0,
    "average_transaction_value":0.0,
    "token_holder":4680.0,
    "time":1620172800000
  },
  {
    "price":10.8567997436,
    "volume":400154158.9490665197,
    "marketcap":10864113160.0548400879,
    "zero_balance_addresses_all_time":8018.0,
    "unique_addresses_all_time":12698.0,
    "new_addresses":0.0,
    "active_addresses":0.0,
    "transaction_count":0.0,
    "transaction_count_all_time":0.0,
    "large_transaction_count":0.0,
    "average_transaction_value":0.0,
    "token_holder":4680.0,
    "time":1620259200000
  },
  {
    "price":11.5508913165,
    "volume":757249185.2156877518,
    "marketcap":11543062433.3173599243,
    "zero_balance_addresses_all_time":8018.0,
    "unique_addresses_all_time":12698.0,
    "new_addresses":0.0,
    "active_addresses":0.0,
    "transaction_count":0.0,
    "transaction_count_all_time":0.0,
    "large_transaction_count":0.0,
    "average_transaction_value":0.0,
    "token_holder":4680.0,
    "time":1620345600000
  },
  {
    "price":12.4097098934,
    "volume":720844776.7569944859,
    "marketcap":12460186603.2742500305,
    "zero_balance_addresses_all_time":8018.0,
    "unique_addresses_all_time":12698.0,
    "new_addresses":0.0,
    "active_addresses":0.0,
    "transaction_count":0.0,
    "transaction_count_all_time":0.0,
    "large_transaction_count":0.0,
    "average_transaction_value":0.0,
    "token_holder":4680.0,
    "time":1620432000000
  },
  {
    "price":11.9506928998,
    "volume":538848395.810557127,
    "marketcap":11950692899.7857494354,
    "zero_balance_addresses_all_time":8018.0,
    "unique_addresses_all_time":12698.0,
    "new_addresses":0.0,
    "active_addresses":0.0,
    "transaction_count":0.0,
    "transaction_count_all_time":0.0,
    "large_transaction_count":0.0,
    "average_transaction_value":0.0,
    "token_holder":4680.0,
    "time":1620518400000
  },
  {
    "price":10.5819714403,
    "volume":563014802.716401577,
    "marketcap":10571347917.7119693756,
    "zero_balance_addresses_all_time":8018.0,
    "unique_addresses_all_time":12698.0,
    "new_addresses":0.0,
    "active_addresses":0.0,
    "transaction_count":0.0,
    "transaction_count_all_time":0.0,
    "large_transaction_count":0.0,
    "average_transaction_value":0.0,
    "token_holder":4680.0,
    "time":1620604800000
  },
  {
    "price":10.8378874265,
    "volume":447140704.4303837419,
    "marketcap":10848399961.4256401062,
    "zero_balance_addresses_all_time":8018.0,
    "unique_addresses_all_time":12698.0,
    "new_addresses":0.0,
    "active_addresses":0.0,
    "transaction_count":0.0,
    "transaction_count_all_time":0.0,
    "large_transaction_count":0.0,
    "average_transaction_value":0.0,
    "token_holder":4680.0,
    "time":1620691200000
  },
  {
    "price":9.6745057692,
    "volume":512324757.2505118847,
    "marketcap":9702553369.8045082092,
    "zero_balance_addresses_all_time":8018.0,
    "unique_addresses_all_time":12698.0,
    "new_addresses":0.0,
    "active_addresses":0.0,
    "transaction_count":0.0,
    "transaction_count_all_time":0.0,
    "large_transaction_count":0.0,
    "average_transaction_value":0.0,
    "token_holder":4680.0,
    "time":1620777600000
  },
  {
    "price":9.7658167744,
    "volume":660946140.0420387983,
    "marketcap":9677115755.110994339,
    "zero_balance_addresses_all_time":8018.0,
    "unique_addresses_all_time":12698.0,
    "new_addresses":0.0,
    "active_addresses":0.0,
    "transaction_count":0.0,
    "transaction_count_all_time":0.0,
    "large_transaction_count":0.0,
    "average_transaction_value":0.0,
    "token_holder":4680.0,
    "time":1620864000000
  },
  {
    "price":10.0388815357,
    "volume":382742697.6521843672,
    "marketcap":10032956873.7781295776,
    "zero_balance_addresses_all_time":8018.0,
    "unique_addresses_all_time":12698.0,
    "new_addresses":0.0,
    "active_addresses":0.0,
    "transaction_count":0.0,
    "transaction_count_all_time":0.0,
    "large_transaction_count":0.0,
    "average_transaction_value":0.0,
    "token_holder":4680.0,
    "time":1620950400000
  },
  {
    "price":9.2916236074,
    "volume":291510796.5479806662,
    "marketcap":9303797214.7118835449,
    "zero_balance_addresses_all_time":8018.0,
    "unique_addresses_all_time":12698.0,
    "new_addresses":0.0,
    "active_addresses":0.0,
    "transaction_count":0.0,
    "transaction_count_all_time":0.0,
    "large_transaction_count":0.0,
    "average_transaction_value":0.0,
    "token_holder":4680.0,
    "time":1621036800000
  },
  {
    "price":9.5035983256,
    "volume":414803883.6662465334,
    "marketcap":9463228381.2745838165,
    "zero_balance_addresses_all_time":8018.0,
    "unique_addresses_all_time":12698.0,
    "new_addresses":0.0,
    "active_addresses":0.0,
    "transaction_count":0.0,
    "transaction_count_all_time":0.0,
    "large_transaction_count":0.0,
    "average_transaction_value":0.0,
    "token_holder":4680.0,
    "time":1621123200000
  },
  {
    "price":9.6315174129,
    "volume":611940332.1557745934,
    "marketcap":9786515805.7749462128,
    "zero_balance_addresses_all_time":8018.0,
    "unique_addresses_all_time":12698.0,
    "new_addresses":0.0,
    "active_addresses":0.0,
    "transaction_count":0.0,
    "transaction_count_all_time":0.0,
    "large_transaction_count":0.0,
    "average_transaction_value":0.0,
    "token_holder":4680.0,
    "time":1621209600000
  },
  {
    "price":9.8130916304,
    "volume":355359714.495980978,
    "marketcap":9765787684.5594673157,
    "zero_balance_addresses_all_time":8018.0,
    "unique_addresses_all_time":12698.0,
    "new_addresses":0.0,
    "active_addresses":0.0,
    "transaction_count":0.0,
    "transaction_count_all_time":0.0,
    "large_transaction_count":0.0,
    "average_transaction_value":0.0,
    "token_holder":4680.0,
    "time":1621296000000
  },
  {
    "price":6.0295906359,
    "volume":991370700.6987013817,
    "marketcap":6165545822.6585988998,
    "zero_balance_addresses_all_time":8018.0,
    "unique_addresses_all_time":12698.0,
    "new_addresses":0.0,
    "active_addresses":0.0,
    "transaction_count":0.0,
    "transaction_count_all_time":0.0,
    "large_transaction_count":0.0,
    "average_transaction_value":0.0,
    "token_holder":4680.0,
    "time":1621382400000
  },
  {
    "price":7.2367714652,
    "volume":766164791.9090261459,
    "marketcap":7197032005.2808446884,
    "zero_balance_addresses_all_time":8018.0,
    "unique_addresses_all_time":12698.0,
    "new_addresses":0.0,
    "active_addresses":0.0,
    "transaction_count":0.0,
    "transaction_count_all_time":0.0,
    "large_transaction_count":0.0,
    "average_transaction_value":0.0,
    "token_holder":4680.0,
    "time":1621468800000
  }
]