[
  {
    "coin_id":18069,
    "coin_name":"STEPN",
    "symbol":"GMT",
    "slug":"green-metaverse-token",
    "image":"https:\/\/raw.githubusercontent.com\/intnode\/mock-data-coinint\/master\/img\/coin\/green-metaverse-token.png",
    "current_price":0.1907266291,
    "convert_symbol":"USD",
    "circulating_supply":952322297.0031728745,
    "total_supply":5484188977.0031728745,
    "max_supply":6000000000.0,
    "market_cap":181633221.5455600321,
    "fully_diluted_market_cap":1144359774.7300000191,
    "dominance":0.0175,
    "rank":127,
    "percent_change_1h":0.64074851,
    "percent_change_24h":3.88957486,
    "percent_change_7d":-17.57038581,
    "percent_change_30d":-30.87323272,
    "volume_24h":22318514.1283467598,
    "volume_change_24h":-55.1682,
    "last_updated":1686866280000
  },
  {
    "coin_id":10180,
    "coin_name":"Gomining",
    "symbol":"GMT",
    "slug":"gomining-token",
    "image":"https:\/\/raw.githubusercontent.com\/intnode\/mock-data-coinint\/master\/img\/coin\/gomining-token.png",
    "current_price":0.0881697221,
    "convert_symbol":"USD",
    "circulating_supply":274472650.1600000262,
    "total_supply":436915240.0,
    "max_supply":436915240.0,
    "market_cap":24200177.2927558422,
    "fully_diluted_market_cap":38522695.299999997,
    "dominance":0,
    "rank":515,
    "percent_change_1h":0.03146385,
    "percent_change_24h":2.47658312,
    "percent_change_7d":-3.46497037,
    "percent_change_30d":-9.10456536,
    "volume_24h":1097313.7062637,
    "volume_change_24h":-24.6728,
    "last_updated":1686866280000
  }
]