[
  {
    "coin_id":5488,
    "coin_name":"JUST",
    "symbol":"JST",
    "slug":"just",
    "image":"https:\/\/raw.githubusercontent.com\/intnode\/mock-data-coinint\/master\/img\/coin\/just.png",
    "current_price":0.0331916869,
    "convert_symbol":"USD",
    "circulating_supply":8902080000.0,
    "total_supply":9900000000.0,
    "max_supply":9900000000.0,
    "market_cap":295475051.705360353,
    "fully_diluted_market_cap":328597699.8500000238,
    "dominance":0.0151,
    "rank":185,
    "percent_change_1h":-0.17014521,
    "percent_change_24h":-2.42330936,
    "percent_change_7d":7.56687163,
    "percent_change_30d":13.22326658,
    "volume_24h":42937310.9767441675,
    "volume_change_24h":15.28,
    "quote":{
      "USD":{
        "price":0.0331916869,
        "volume_24h":42937310.9767441675,
        "volume_change_24h":15.28,
        "percent_change_1h":-0.17014521,
        "percent_change_24h":-2.42330936,
        "percent_change_7d":7.56687163,
        "percent_change_30d":13.22326658,
        "percent_change_60d":3.83811958,
        "percent_change_90d":10.64555826,
        "market_cap":295475051.705360353,
        "market_cap_dominance":0.0151,
        "fully_diluted_market_cap":328597699.8500000238,
        "tvl":null,
        "last_updated":"2024-02-20T16:59:00.000Z"
      },
      "BTC":{
        "price":0.0000006461,
        "volume_24h":835.8321363478,
        "volume_change_24h":15.28,
        "percent_change_1h":-0.17014521,
        "percent_change_24h":-2.42330936,
        "percent_change_7d":7.56687163,
        "percent_change_30d":13.22326658,
        "percent_change_60d":3.83811958,
        "percent_change_90d":10.64555826,
        "market_cap":5751.8167320292,
        "market_cap_dominance":0.0151,
        "fully_diluted_market_cap":6396.5933407746,
        "tvl":null,
        "last_updated":"2024-02-20T16:59:00.000Z"
      }
    },
    "last_updated":1708448340000
  }
]