[
  {
    "time":1700762400,
    "close":3.331
  },
  {
    "time":1700766000,
    "close":3.32
  },
  {
    "time":1700769600,
    "close":3.32
  },
  {
    "time":1700773200,
    "close":3.328
  },
  {
    "time":1700776800,
    "close":3.341
  },
  {
    "time":1700780400,
    "close":3.349
  },
  {
    "time":1700784000,
    "close":3.378
  },
  {
    "time":1700787600,
    "close":3.373
  },
  {
    "time":1700791200,
    "close":3.399
  },
  {
    "time":1700794800,
    "close":3.399
  },
  {
    "time":1700798400,
    "close":3.377
  },
  {
    "time":1700802000,
    "close":3.381
  },
  {
    "time":1700805600,
    "close":3.401
  },
  {
    "time":1700809200,
    "close":3.42
  },
  {
    "time":1700812800,
    "close":3.411
  },
  {
    "time":1700816400,
    "close":3.448
  },
  {
    "time":1700820000,
    "close":3.421
  },
  {
    "time":1700823600,
    "close":3.442
  },
  {
    "time":1700827200,
    "close":3.429
  },
  {
    "time":1700830800,
    "close":3.41
  },
  {
    "time":1700834400,
    "close":3.41
  },
  {
    "time":1700838000,
    "close":3.447
  },
  {
    "time":1700841600,
    "close":3.42
  },
  {
    "time":1700845200,
    "close":3.419
  },
  {
    "time":1700848800,
    "close":3.419
  },
  {
    "time":1700852400,
    "close":3.41
  },
  {
    "time":1700856000,
    "close":3.421
  },
  {
    "time":1700859600,
    "close":3.421
  },
  {
    "time":1700863200,
    "close":3.421
  },
  {
    "time":1700866800,
    "close":3.42
  },
  {
    "time":1700870400,
    "close":3.449
  },
  {
    "time":1700874000,
    "close":3.496
  },
  {
    "time":1700877600,
    "close":3.49
  },
  {
    "time":1700881200,
    "close":3.536
  },
  {
    "time":1700884800,
    "close":3.54
  },
  {
    "time":1700888400,
    "close":3.543
  },
  {
    "time":1700892000,
    "close":3.53
  },
  {
    "time":1700895600,
    "close":3.555
  },
  {
    "time":1700899200,
    "close":3.52
  },
  {
    "time":1700902800,
    "close":3.5
  },
  {
    "time":1700906400,
    "close":3.481
  },
  {
    "time":1700910000,
    "close":3.476
  },
  {
    "time":1700913600,
    "close":3.51
  },
  {
    "time":1700917200,
    "close":3.5
  },
  {
    "time":1700920800,
    "close":3.53
  },
  {
    "time":1700924400,
    "close":3.537
  },
  {
    "time":1700928000,
    "close":3.52
  },
  {
    "time":1700931600,
    "close":3.54
  },
  {
    "time":1700935200,
    "close":3.52
  },
  {
    "time":1700938800,
    "close":3.53
  },
  {
    "time":1700942400,
    "close":3.55
  },
  {
    "time":1700946000,
    "close":3.57
  },
  {
    "time":1700949600,
    "close":3.56
  },
  {
    "time":1700953200,
    "close":3.61
  },
  {
    "time":1700956800,
    "close":3.58
  },
  {
    "time":1700960400,
    "close":3.546
  },
  {
    "time":1700964000,
    "close":3.55
  },
  {
    "time":1700967600,
    "close":3.537
  },
  {
    "time":1700971200,
    "close":3.551
  },
  {
    "time":1700974800,
    "close":3.56
  },
  {
    "time":1700978400,
    "close":3.541
  },
  {
    "time":1700982000,
    "close":3.53
  },
  {
    "time":1700985600,
    "close":3.53
  },
  {
    "time":1700989200,
    "close":3.53
  },
  {
    "time":1700992800,
    "close":3.491
  },
  {
    "time":1700996400,
    "close":3.472
  },
  {
    "time":1701000000,
    "close":3.507
  },
  {
    "time":1701003600,
    "close":3.52
  },
  {
    "time":1701007200,
    "close":3.47
  },
  {
    "time":1701010800,
    "close":3.433
  },
  {
    "time":1701014400,
    "close":3.409
  },
  {
    "time":1701018000,
    "close":3.41
  },
  {
    "time":1701021600,
    "close":3.4
  },
  {
    "time":1701025200,
    "close":3.42
  },
  {
    "time":1701028800,
    "close":3.438
  },
  {
    "time":1701032400,
    "close":3.43
  },
  {
    "time":1701036000,
    "close":3.46
  },
  {
    "time":1701039600,
    "close":3.43
  },
  {
    "time":1701043200,
    "close":3.5
  },
  {
    "time":1701046800,
    "close":3.431
  },
  {
    "time":1701050400,
    "close":3.391
  },
  {
    "time":1701054000,
    "close":3.369
  },
  {
    "time":1701057600,
    "close":3.391
  },
  {
    "time":1701061200,
    "close":3.399
  },
  {
    "time":1701064800,
    "close":3.36
  },
  {
    "time":1701068400,
    "close":3.352
  },
  {
    "time":1701072000,
    "close":3.359
  },
  {
    "time":1701075600,
    "close":3.379
  },
  {
    "time":1701079200,
    "close":3.317
  },
  {
    "time":1701082800,
    "close":3.34
  },
  {
    "time":1701086400,
    "close":3.348
  },
  {
    "time":1701090000,
    "close":3.358
  },
  {
    "time":1701093600,
    "close":3.288
  },
  {
    "time":1701097200,
    "close":3.286
  },
  {
    "time":1701100800,
    "close":3.33
  },
  {
    "time":1701104400,
    "close":3.32
  },
  {
    "time":1701108000,
    "close":3.309
  },
  {
    "time":1701111600,
    "close":3.286
  },
  {
    "time":1701115200,
    "close":3.29
  },
  {
    "time":1701118800,
    "close":3.321
  },
  {
    "time":1701122400,
    "close":3.33
  },
  {
    "time":1701126000,
    "close":3.35
  },
  {
    "time":1701129600,
    "close":3.352
  },
  {
    "time":1701133200,
    "close":3.34
  },
  {
    "time":1701136800,
    "close":3.33
  },
  {
    "time":1701140400,
    "close":3.337
  },
  {
    "time":1701144000,
    "close":3.29
  },
  {
    "time":1701147600,
    "close":3.25
  },
  {
    "time":1701151200,
    "close":3.29
  },
  {
    "time":1701154800,
    "close":3.28
  },
  {
    "time":1701158400,
    "close":3.28
  },
  {
    "time":1701162000,
    "close":3.302
  },
  {
    "time":1701165600,
    "close":3.3
  },
  {
    "time":1701169200,
    "close":3.329
  },
  {
    "time":1701172800,
    "close":3.32
  },
  {
    "time":1701176400,
    "close":3.352
  },
  {
    "time":1701180000,
    "close":3.366
  },
  {
    "time":1701183600,
    "close":3.368
  },
  {
    "time":1701187200,
    "close":3.41
  },
  {
    "time":1701190800,
    "close":3.41
  },
  {
    "time":1701194400,
    "close":3.4
  },
  {
    "time":1701198000,
    "close":3.42
  },
  {
    "time":1701201600,
    "close":3.429
  },
  {
    "time":1701205200,
    "close":3.419
  },
  {
    "time":1701208800,
    "close":3.41
  },
  {
    "time":1701212400,
    "close":3.4
  },
  {
    "time":1701216000,
    "close":3.43
  },
  {
    "time":1701219600,
    "close":3.41
  },
  {
    "time":1701223200,
    "close":3.39
  },
  {
    "time":1701226800,
    "close":3.39
  },
  {
    "time":1701230400,
    "close":3.4
  },
  {
    "time":1701234000,
    "close":3.398
  },
  {
    "time":1701237600,
    "close":3.42
  },
  {
    "time":1701241200,
    "close":3.42
  },
  {
    "time":1701244800,
    "close":3.438
  },
  {
    "time":1701248400,
    "close":3.444
  },
  {
    "time":1701252000,
    "close":3.386
  },
  {
    "time":1701255600,
    "close":3.408
  },
  {
    "time":1701259200,
    "close":3.412
  },
  {
    "time":1701262800,
    "close":3.401
  },
  {
    "time":1701266400,
    "close":3.385
  },
  {
    "time":1701270000,
    "close":3.4
  },
  {
    "time":1701273600,
    "close":3.38
  },
  {
    "time":1701277200,
    "close":3.4
  },
  {
    "time":1701280800,
    "close":3.409
  },
  {
    "time":1701284400,
    "close":3.391
  },
  {
    "time":1701288000,
    "close":3.38
  },
  {
    "time":1701291600,
    "close":3.381
  },
  {
    "time":1701295200,
    "close":3.41
  },
  {
    "time":1701298800,
    "close":3.4
  },
  {
    "time":1701302400,
    "close":3.444
  },
  {
    "time":1701306000,
    "close":3.401
  },
  {
    "time":1701309600,
    "close":3.42
  },
  {
    "time":1701313200,
    "close":3.4
  },
  {
    "time":1701316800,
    "close":3.399
  },
  {
    "time":1701320400,
    "close":3.39
  },
  {
    "time":1701324000,
    "close":3.426
  },
  {
    "time":1701327600,
    "close":3.409
  },
  {
    "time":1701331200,
    "close":3.396
  },
  {
    "time":1701334800,
    "close":3.372
  },
  {
    "time":1701338400,
    "close":3.385
  },
  {
    "time":1701342000,
    "close":3.428
  },
  {
    "time":1701345600,
    "close":3.424
  },
  {
    "time":1701349200,
    "close":3.399
  },
  {
    "time":1701352800,
    "close":3.398
  },
  {
    "time":1701356400,
    "close":3.4
  },
  {
    "time":1701360000,
    "close":3.4
  },
  {
    "time":1701363600,
    "close":3.402
  }
]