[
  {
    "time":1706551200,
    "close":1.564
  },
  {
    "time":1706554800,
    "close":1.547
  },
  {
    "time":1706558400,
    "close":1.543
  },
  {
    "time":1706562000,
    "close":1.545
  },
  {
    "time":1706565600,
    "close":1.565
  },
  {
    "time":1706569200,
    "close":1.563
  },
  {
    "time":1706572800,
    "close":1.551
  },
  {
    "time":1706576400,
    "close":1.596
  },
  {
    "time":1706580000,
    "close":1.619
  },
  {
    "time":1706583600,
    "close":1.6
  },
  {
    "time":1706587200,
    "close":1.599
  },
  {
    "time":1706590800,
    "close":1.61
  },
  {
    "time":1706594400,
    "close":1.609
  },
  {
    "time":1706598000,
    "close":1.619
  },
  {
    "time":1706601600,
    "close":1.598
  },
  {
    "time":1706605200,
    "close":1.617
  },
  {
    "time":1706608800,
    "close":1.626
  },
  {
    "time":1706612400,
    "close":1.61
  },
  {
    "time":1706616000,
    "close":1.556
  },
  {
    "time":1706619600,
    "close":1.552
  },
  {
    "time":1706623200,
    "close":1.559
  },
  {
    "time":1706626800,
    "close":1.538
  },
  {
    "time":1706630400,
    "close":1.533
  },
  {
    "time":1706634000,
    "close":1.548
  },
  {
    "time":1706637600,
    "close":1.542
  },
  {
    "time":1706641200,
    "close":1.543
  },
  {
    "time":1706644800,
    "close":1.547
  },
  {
    "time":1706648400,
    "close":1.536
  },
  {
    "time":1706652000,
    "close":1.522
  },
  {
    "time":1706655600,
    "close":1.545
  },
  {
    "time":1706659200,
    "close":1.522
  },
  {
    "time":1706662800,
    "close":1.517
  },
  {
    "time":1706666400,
    "close":1.536
  },
  {
    "time":1706670000,
    "close":1.532
  },
  {
    "time":1706673600,
    "close":1.562
  },
  {
    "time":1706677200,
    "close":1.568
  },
  {
    "time":1706680800,
    "close":1.592
  },
  {
    "time":1706684400,
    "close":1.629
  },
  {
    "time":1706688000,
    "close":1.614
  },
  {
    "time":1706691600,
    "close":1.584
  },
  {
    "time":1706695200,
    "close":1.553
  },
  {
    "time":1706698800,
    "close":1.567
  },
  {
    "time":1706702400,
    "close":1.609
  },
  {
    "time":1706706000,
    "close":1.6
  },
  {
    "time":1706709600,
    "close":1.616
  },
  {
    "time":1706713200,
    "close":1.605
  },
  {
    "time":1706716800,
    "close":1.598
  },
  {
    "time":1706720400,
    "close":1.593
  },
  {
    "time":1706724000,
    "close":1.59
  },
  {
    "time":1706727600,
    "close":1.602
  },
  {
    "time":1706731200,
    "close":1.549
  },
  {
    "time":1706734800,
    "close":1.547
  },
  {
    "time":1706738400,
    "close":1.551
  },
  {
    "time":1706742000,
    "close":1.518
  },
  {
    "time":1706745600,
    "close":1.549
  },
  {
    "time":1706749200,
    "close":1.515
  },
  {
    "time":1706752800,
    "close":1.53
  },
  {
    "time":1706756400,
    "close":1.456
  },
  {
    "time":1706760000,
    "close":1.469
  },
  {
    "time":1706763600,
    "close":1.473
  },
  {
    "time":1706767200,
    "close":1.474
  },
  {
    "time":1706770800,
    "close":1.477
  },
  {
    "time":1706774400,
    "close":1.469
  },
  {
    "time":1706778000,
    "close":1.445
  },
  {
    "time":1706781600,
    "close":1.455
  },
  {
    "time":1706785200,
    "close":1.449
  },
  {
    "time":1706788800,
    "close":1.447
  },
  {
    "time":1706792400,
    "close":1.453
  },
  {
    "time":1706796000,
    "close":1.477
  },
  {
    "time":1706799600,
    "close":1.464
  },
  {
    "time":1706803200,
    "close":1.457
  },
  {
    "time":1706806800,
    "close":1.509
  },
  {
    "time":1706810400,
    "close":1.511
  },
  {
    "time":1706814000,
    "close":1.548
  },
  {
    "time":1706817600,
    "close":1.54
  },
  {
    "time":1706821200,
    "close":1.524
  },
  {
    "time":1706824800,
    "close":1.526
  },
  {
    "time":1706828400,
    "close":1.525
  },
  {
    "time":1706832000,
    "close":1.512
  },
  {
    "time":1706835600,
    "close":1.513
  },
  {
    "time":1706839200,
    "close":1.518
  },
  {
    "time":1706842800,
    "close":1.508
  },
  {
    "time":1706846400,
    "close":1.499
  },
  {
    "time":1706850000,
    "close":1.502
  },
  {
    "time":1706853600,
    "close":1.506
  },
  {
    "time":1706857200,
    "close":1.508
  },
  {
    "time":1706860800,
    "close":1.487
  },
  {
    "time":1706864400,
    "close":1.474
  },
  {
    "time":1706868000,
    "close":1.477
  },
  {
    "time":1706871600,
    "close":1.472
  },
  {
    "time":1706875200,
    "close":1.461
  },
  {
    "time":1706878800,
    "close":1.455
  },
  {
    "time":1706882400,
    "close":1.455
  },
  {
    "time":1706886000,
    "close":1.472
  },
  {
    "time":1706889600,
    "close":1.483
  },
  {
    "time":1706893200,
    "close":1.468
  },
  {
    "time":1706896800,
    "close":1.462
  },
  {
    "time":1706900400,
    "close":1.465
  },
  {
    "time":1706904000,
    "close":1.463
  },
  {
    "time":1706907600,
    "close":1.467
  },
  {
    "time":1706911200,
    "close":1.474
  },
  {
    "time":1706914800,
    "close":1.462
  },
  {
    "time":1706918400,
    "close":1.458
  },
  {
    "time":1706922000,
    "close":1.458
  },
  {
    "time":1706925600,
    "close":1.416
  },
  {
    "time":1706929200,
    "close":1.409
  },
  {
    "time":1706932800,
    "close":1.412
  },
  {
    "time":1706936400,
    "close":1.411
  },
  {
    "time":1706940000,
    "close":1.402
  },
  {
    "time":1706943600,
    "close":1.397
  },
  {
    "time":1706947200,
    "close":1.39
  },
  {
    "time":1706950800,
    "close":1.408
  },
  {
    "time":1706954400,
    "close":1.402
  },
  {
    "time":1706958000,
    "close":1.399
  },
  {
    "time":1706961600,
    "close":1.402
  },
  {
    "time":1706965200,
    "close":1.421
  },
  {
    "time":1706968800,
    "close":1.413
  },
  {
    "time":1706972400,
    "close":1.423
  },
  {
    "time":1706976000,
    "close":1.465
  },
  {
    "time":1706979600,
    "close":1.457
  },
  {
    "time":1706983200,
    "close":1.436
  },
  {
    "time":1706986800,
    "close":1.453
  },
  {
    "time":1706990400,
    "close":1.442
  },
  {
    "time":1706994000,
    "close":1.443
  },
  {
    "time":1706997600,
    "close":1.432
  },
  {
    "time":1707001200,
    "close":1.437
  },
  {
    "time":1707004800,
    "close":1.454
  },
  {
    "time":1707008400,
    "close":1.474
  },
  {
    "time":1707012000,
    "close":1.475
  },
  {
    "time":1707015600,
    "close":1.479
  },
  {
    "time":1707019200,
    "close":1.464
  },
  {
    "time":1707022800,
    "close":1.46
  },
  {
    "time":1707026400,
    "close":1.464
  },
  {
    "time":1707030000,
    "close":1.475
  },
  {
    "time":1707033600,
    "close":1.484
  },
  {
    "time":1707037200,
    "close":1.515
  },
  {
    "time":1707040800,
    "close":1.506
  },
  {
    "time":1707044400,
    "close":1.503
  },
  {
    "time":1707048000,
    "close":1.497
  },
  {
    "time":1707051600,
    "close":1.5
  },
  {
    "time":1707055200,
    "close":1.503
  },
  {
    "time":1707058800,
    "close":1.524
  },
  {
    "time":1707062400,
    "close":1.53
  },
  {
    "time":1707066000,
    "close":1.525
  },
  {
    "time":1707069600,
    "close":1.515
  },
  {
    "time":1707073200,
    "close":1.497
  },
  {
    "time":1707076800,
    "close":1.501
  },
  {
    "time":1707080400,
    "close":1.489
  },
  {
    "time":1707084000,
    "close":1.475
  },
  {
    "time":1707087600,
    "close":1.464
  },
  {
    "time":1707091200,
    "close":1.465
  },
  {
    "time":1707094800,
    "close":1.44
  },
  {
    "time":1707098400,
    "close":1.44
  },
  {
    "time":1707102000,
    "close":1.466
  },
  {
    "time":1707105600,
    "close":1.481
  },
  {
    "time":1707109200,
    "close":1.508
  },
  {
    "time":1707112800,
    "close":1.513
  },
  {
    "time":1707116400,
    "close":1.515
  },
  {
    "time":1707120000,
    "close":1.522
  },
  {
    "time":1707123600,
    "close":1.533
  },
  {
    "time":1707127200,
    "close":1.554
  },
  {
    "time":1707130800,
    "close":1.543
  },
  {
    "time":1707134400,
    "close":1.545
  },
  {
    "time":1707138000,
    "close":1.637
  },
  {
    "time":1707141600,
    "close":1.617
  },
  {
    "time":1707145200,
    "close":1.566
  },
  {
    "time":1707148800,
    "close":1.599
  },
  {
    "time":1707152400,
    "close":1.602
  }
]