[
  {
    "coin_id":1934,
    "coin_name":"Loopring",
    "symbol":"LRC",
    "slug":"loopring",
    "image":"https:\/\/raw.githubusercontent.com\/intnode\/mock-data-coinint\/master\/img\/coin\/loopring.png",
    "current_price":0.228094232,
    "convert_symbol":"USD",
    "circulating_supply":1331523612.2462103367,
    "total_supply":1373873397.4424574375,
    "max_supply":1374513896.0,
    "market_cap":303712855.6672508121,
    "fully_diluted_market_cap":313518691.4200000167,
    "dominance":0.0255,
    "rank":101,
    "percent_change_1h":-0.12078884,
    "percent_change_24h":0.14718607,
    "percent_change_7d":-6.02665056,
    "percent_change_30d":9.58401338,
    "volume_24h":11431311.6474245302,
    "volume_change_24h":-24.7934,
    "last_updated":1689135060000
  }
]