[
  {
    "coin_id":2577,
    "coin_name":"Ravencoin",
    "symbol":"RVN",
    "slug":"ravencoin",
    "image":"https:\/\/raw.githubusercontent.com\/intnode\/mock-data-coinint\/master\/img\/coin\/ravencoin.png",
    "current_price":0.0181110418,
    "convert_symbol":"USD",
    "circulating_supply":13474435897.5639190674,
    "total_supply":13474435897.5639190674,
    "max_supply":21000000000.0,
    "market_cap":244036072.0974641442,
    "fully_diluted_market_cap":380331878.3100000024,
    "dominance":0.0147,
    "rank":180,
    "percent_change_1h":-0.15769396,
    "percent_change_24h":1.18317096,
    "percent_change_7d":-1.8567548,
    "percent_change_30d":-10.34161958,
    "volume_24h":6073941.8817044003,
    "volume_change_24h":-21.1343,
    "quote":{
      "USD":{
        "price":0.0181110418,
        "volume_24h":6073941.8817044003,
        "volume_change_24h":-21.1343,
        "percent_change_1h":-0.15769396,
        "percent_change_24h":1.18317096,
        "percent_change_7d":-1.8567548,
        "percent_change_30d":-10.34161958,
        "percent_change_60d":-7.87884933,
        "percent_change_90d":3.53986894,
        "market_cap":244036072.0974641442,
        "market_cap_dominance":0.0147,
        "fully_diluted_market_cap":380331878.3100000024,
        "tvl":null,
        "last_updated":"2024-02-02T16:58:00.000Z"
      },
      "BTC":{
        "price":0.0000004192,
        "volume_24h":140.572793371,
        "volume_change_24h":-21.1343,
        "percent_change_1h":-0.15769396,
        "percent_change_24h":1.18317096,
        "percent_change_7d":-1.8567548,
        "percent_change_30d":-10.34161958,
        "percent_change_60d":-7.87884933,
        "percent_change_90d":3.53986894,
        "market_cap":5647.8697040808,
        "market_cap_dominance":0.0147,
        "fully_diluted_market_cap":8802.2433509145,
        "tvl":null,
        "last_updated":"2024-02-02T16:59:00.000Z"
      }
    },
    "last_updated":1706893080000
  }
]