[
  {
    "coin_id":2299,
    "coin_name":"aelf",
    "symbol":"ELF",
    "slug":"aelf",
    "image":"https:\/\/raw.githubusercontent.com\/intnode\/mock-data-coinint\/master\/img\/coin\/aelf.png",
    "current_price":0.6010506855,
    "convert_symbol":"USD",
    "circulating_supply":714767544.7841900587,
    "total_supply":1000000000.0,
    "max_supply":1000000000.0,
    "market_cap":429611522.7439855933,
    "fully_diluted_market_cap":601050685.4700000286,
    "dominance":0.0266,
    "rank":121,
    "percent_change_1h":0.14605714,
    "percent_change_24h":2.93185313,
    "percent_change_7d":6.26805407,
    "percent_change_30d":-0.927366,
    "volume_24h":14281822.1815012097,
    "volume_change_24h":131.0597,
    "quote":{
      "USD":{
        "price":0.6010506855,
        "volume_24h":14281822.1815012097,
        "volume_change_24h":131.0597,
        "percent_change_1h":0.14605714,
        "percent_change_24h":2.93185313,
        "percent_change_7d":6.26805407,
        "percent_change_30d":-0.927366,
        "percent_change_60d":34.3491977,
        "percent_change_90d":65.29080851,
        "market_cap":429611522.7439855933,
        "market_cap_dominance":0.0266,
        "fully_diluted_market_cap":601050685.4700000286,
        "tvl":null,
        "last_updated":"2024-01-27T16:59:00.000Z"
      },
      "BTC":{
        "price":0.0000143728,
        "volume_24h":341.5183720783,
        "volume_change_24h":131.0597,
        "percent_change_1h":0.14605714,
        "percent_change_24h":2.93185313,
        "percent_change_7d":6.26805407,
        "percent_change_30d":-0.927366,
        "percent_change_60d":34.3491977,
        "percent_change_90d":65.29080851,
        "market_cap":10273.2148607514,
        "market_cap_dominance":0.0266,
        "fully_diluted_market_cap":14372.8054466427,
        "tvl":null,
        "last_updated":"2024-01-27T16:59:00.000Z"
      }
    },
    "last_updated":1706374740000
  }
]