[
  {
    "coin_id":3077,
    "coin_name":"VeChain",
    "symbol":"VET",
    "slug":"vechain",
    "image":"https:\/\/raw.githubusercontent.com\/intnode\/mock-data-coinint\/master\/img\/coin\/vechain.png",
    "current_price":0.0179085802,
    "convert_symbol":"USD",
    "circulating_supply":72714516834.0,
    "total_supply":85985041177.0,
    "max_supply":86712634466.0,
    "market_cap":1302213753.7855553627,
    "fully_diluted_market_cap":1552900165.5399999619,
    "dominance":0.1117,
    "rank":38,
    "percent_change_1h":0.55907582,
    "percent_change_24h":-0.30918572,
    "percent_change_7d":-4.83135229,
    "percent_change_30d":-4.24754714,
    "volume_24h":26297613.5572679006,
    "volume_change_24h":11.4559,
    "last_updated":1691377740000
  }
]