[
  {
    "coin_id":1437,
    "coin_name":"Zcash",
    "symbol":"ZEC",
    "slug":"zcash",
    "image":"https:\/\/raw.githubusercontent.com\/intnode\/mock-data-coinint\/master\/img\/coin\/zcash.png",
    "current_price":33.9418554693,
    "convert_symbol":"USD",
    "circulating_supply":16328268.75,
    "total_supply":16328268.75,
    "max_supply":21000000.0,
    "market_cap":554211737.976238966,
    "fully_diluted_market_cap":712778964.8600000143,
    "dominance":0.0337,
    "rank":98,
    "percent_change_1h":-0.88005014,
    "percent_change_24h":1.3868578,
    "percent_change_7d":11.00155676,
    "percent_change_30d":19.11312977,
    "volume_24h":68796018.030334428,
    "volume_change_24h":-1.3954,
    "quote":{
      "USD":{
        "price":33.9418554693,
        "volume_24h":68796018.030334428,
        "volume_change_24h":-1.3954,
        "percent_change_1h":-0.88005014,
        "percent_change_24h":1.3868578,
        "percent_change_7d":11.00155676,
        "percent_change_30d":19.11312977,
        "percent_change_60d":32.39945642,
        "percent_change_90d":39.1116601,
        "market_cap":554211737.976238966,
        "market_cap_dominance":0.0337,
        "fully_diluted_market_cap":712778964.8600000143,
        "tvl":null,
        "last_updated":"2023-12-09T16:57:00.000Z"
      },
      "BTC":{
        "price":0.0007715523,
        "volume_24h":1561.2149112191,
        "volume_change_24h":-0.6469,
        "percent_change_1h":-0.83090043,
        "percent_change_24h":1.56990855,
        "percent_change_7d":10.95412971,
        "percent_change_30d":19.19786055,
        "percent_change_60d":32.5727794,
        "percent_change_90d":39.07731247,
        "market_cap":12598.1136607666,
        "market_cap_dominance":0.0338,
        "fully_diluted_market_cap":16202.5987523679,
        "tvl":null,
        "last_updated":"2023-12-09T16:59:00.000Z"
      }
    },
    "last_updated":1702141140000
  }
]